hwcomponents/__init__.py
hwcomponents/_logging.py
hwcomponents/_model_wrapper.py
hwcomponents/_util.py
hwcomponents/_version.py
hwcomponents/_version_scheme.py
hwcomponents/find_models.py
hwcomponents/hwcomponents.py
hwcomponents/model.py
hwcomponents/select_models.py
hwcomponents/scaling/__init__.py
hwcomponents/scaling/scalefuncs.py
hwcomponents/scaling/techscaling.py
hwcomponents-1.0.76.dist-info/METADATA
hwcomponents-1.0.76.dist-info/WHEEL
hwcomponents-1.0.76.dist-info/entry_points.txt
hwcomponents-1.0.76.dist-info/top_level.txt
hwcomponents-1.0.76.dist-info/zip-safe
hwcomponents-1.0.76.dist-info/RECORD
