Metadata-Version: 2.4
Name: hwcomponents
Version: 1.0.76
Summary: Hardware Component Area, Energy, Latency, and Leak Power Models
Author-email: Tanner Andrulis <andrulis@mit.edu>
License-Expression: MIT
Requires-Python: >=3.12
